vitya/__init__.py
vitya/error_description.py
vitya/errors.py
vitya/errors_base.py
vitya/py.typed
vitya/pydantic_fields.py
vitya/typing_helpers.py
vitya/validators.py
vitya/payment_order/__init__.py
vitya/payment_order/enums.py
vitya/payment_order/errors.py
vitya/payment_order/fields.py
vitya/payment_order/validators.py
vitya/payment_order/payments/__init__.py
vitya/payment_order/payments/checkers.py
vitya/payment_order/payments/checks.py
vitya/payment_order/payments/constants.py
vitya/payment_order/payments/tools.py
vitya-0.20.20.dist-info/licenses/LICENSE
vitya-0.20.20.dist-info/METADATA
vitya-0.20.20.dist-info/WHEEL
vitya-0.20.20.dist-info/top_level.txt
vitya-0.20.20.dist-info/RECORD
