Metadata-Version: 2.4
Name: vitya
Version: 0.20.20
Summary: Validators for different russian banking values
Home-page: https://github.com/hicebank/vitya
Author: hicebank.ru
Author-email: inyutin@hicebank.ru
Classifier: Programming Language :: Python :: 3
Classifier: License :: OSI Approved :: MIT License
Classifier: Operating System :: OS Independent
Requires-Python: >=3.8
License-File: LICENSE
Dynamic: author
Dynamic: author-email
Dynamic: classifier
Dynamic: description
Dynamic: description-content-type
Dynamic: home-page
Dynamic: license-file
Dynamic: requires-python
Dynamic: summary
